ccutils/__init__.py
ccutils/ccparser/BaseConfigLine.py
ccutils/ccparser/BaseConfigParser.py
ccutils/ccparser/BaseInterfaceLine.py
ccutils/ccparser/CiscoIosInterfaceLine.py
ccutils/ccparser/CiscoIosParser.py
ccutils/ccparser/ConfigMigration.py
ccutils/ccparser/ConfigToJson.py
ccutils/ccparser/__init__.py
ccutils/cctemplater/CCTemplater.py
ccutils/cctemplater/__init__.py
ccutils/templates/base_config.jinja2
ccutils/templates/vlans.jinja2
ccutils/templates/vrfs.jinja2
ccutils/templates/interface/base_interface.jinja2
ccutils/templates/interface/interfaces.jinja2
ccutils/templates/interface/interfaces_only.jinja2
ccutils/templates/interface/l2_interface.jinja2
ccutils/templates/interface/l3_interface.jinja2
ccutils/templates/routing/static_routes.jinja2
ccutils/utils/CiscoRange.py
ccutils/utils/CustomAnsibleDumper.py
ccutils/utils/ExcelInventory.py
ccutils/utils/JsonValidator.py
ccutils/utils/__init__.py
ccutils/utils/common_utils.py
ccutils/utils/definitions.py
ccutils-0.2.18.dist-info/LICENSE.md
ccutils-0.2.18.dist-info/METADATA
ccutils-0.2.18.dist-info/WHEEL
ccutils-0.2.18.dist-info/top_level.txt
ccutils-0.2.18.dist-info/RECORD
