Metadata-Version: 2.1
Name: ccutils
Version: 0.2.18
Summary: Cisco Configuration Utilities
Home-page: https://github.org/mihudec/ccutils
Author: Miroslav Hudec
Author-email: mijujda@gmail.com
License: UNKNOWN
Platform: UNKNOWN
Requires-Dist: PyYAML (>=5.1)
Requires-Dist: jsonschema
